recursive_parse/__init__.py
recursive_parse/hsc_analysis.py
recursive_parse/json_to_csv.py
recursive_parse/recursive_parse.py
recursive_parse/regex.py
recursive_parse-0.0.2.dist-info/LICENSE
recursive_parse-0.0.2.dist-info/METADATA
recursive_parse-0.0.2.dist-info/WHEEL
recursive_parse-0.0.2.dist-info/top_level.txt
recursive_parse-0.0.2.dist-info/RECORD
