Metadata-Version: 2.1
Name: recursive-parse
Version: 0.0.2
Summary: A script for analyzing tournament replay packs
Home-page: https://github.com/ZephyrBlu/recursive-parse
Author: ZephyrBlu/Luke Holroyd
Author-email: hello@zephyrus.gg
License: UNKNOWN
Platform: UNKNOWN
Classifier: Programming Language :: Python :: 3
Classifier: License :: OSI Approved :: MIT License
Classifier: Operating System :: OS Independent
Requires-Python: >=3.6
